confluence_poster/__init__.py
confluence_poster/__main__.py
confluence_poster/config_loader.py
confluence_poster/config_wizard.py
confluence_poster/convert_utils.py
confluence_poster/file_upload_helpers.py
confluence_poster/main.py
confluence_poster/main_helpers.py
confluence_poster/page_creation_helpers.py
confluence_poster/page_location_helpers.py
confluence_poster/poster_config.py
confluence_poster-1.4.4.dist-info/LICENSE
confluence_poster-1.4.4.dist-info/METADATA
confluence_poster-1.4.4.dist-info/WHEEL
confluence_poster-1.4.4.dist-info/entry_points.txt
confluence_poster-1.4.4.dist-info/top_level.txt
confluence_poster-1.4.4.dist-info/RECORD
