Metadata-Version: 2.1
Name: confluence-poster
Version: 1.4.4
Summary: Script that updates Confluence articles from files written locally
Home-page: https://github.com/VTimofeenko/confluence_poster
Author: Vladimir Timofeenko
Author-email: confluence.poster.maintain@vtimofeenko.com
License: MIT
Project-URL: Bug Reports, https://github.com/VTimofeenko/confluence_poster/issues
Project-URL: Source, https://github.com/VTimofeenko/confluence_poster/
Keywords: confluence api vim
Platform: UNKNOWN
Classifier: Development Status :: 4 - Beta
Classifier: Environment :: Console
Classifier: Topic :: Utilities
Classifier: Topic :: Text Processing
Classifier: Programming Language :: Python :: 3.8
Classifier: License :: OSI Approved :: MIT License
Requires-Python: >=3.8, <4
Requires-Dist: atlassian-python-api (==3.11.0)
Requires-Dist: typer (>=0.3.2)
Requires-Dist: toml
Requires-Dist: requests
Requires-Dist: pyxdg (>=0.26)
Requires-Dist: tomlkit (==0.7.2)
Requires-Dist: click (<7.2.0,>=7.1.1)
Requires-Dist: markdown (==3.3.4)
Provides-Extra: docs
Requires-Dist: jinja2 ; extra == 'docs'
Requires-Dist: typer-cli ; extra == 'docs'
